wikibase_rest_api_client/__init__.py
wikibase_rest_api_client/api/__init__.py
wikibase_rest_api_client/api/aliases/__init__.py
wikibase_rest_api_client/api/aliases/add_item_aliases_in_language.py
wikibase_rest_api_client/api/aliases/add_property_aliases_in_language.py
wikibase_rest_api_client/api/aliases/get_item_aliases.py
wikibase_rest_api_client/api/aliases/get_item_aliases_in_language.py
wikibase_rest_api_client/api/aliases/get_property_aliases.py
wikibase_rest_api_client/api/aliases/get_property_aliases_in_language.py
wikibase_rest_api_client/api/aliases/patch_item_aliases.py
wikibase_rest_api_client/api/aliases/patch_property_aliases.py
wikibase_rest_api_client/api/descriptions/__init__.py
wikibase_rest_api_client/api/descriptions/delete_item_description.py
wikibase_rest_api_client/api/descriptions/delete_property_description.py
wikibase_rest_api_client/api/descriptions/get_item_description.py
wikibase_rest_api_client/api/descriptions/get_item_descriptions.py
wikibase_rest_api_client/api/descriptions/get_property_description.py
wikibase_rest_api_client/api/descriptions/get_property_descriptions.py
wikibase_rest_api_client/api/descriptions/patch_item_descriptions.py
wikibase_rest_api_client/api/descriptions/patch_property_descriptions.py
wikibase_rest_api_client/api/descriptions/replace_item_description.py
wikibase_rest_api_client/api/descriptions/replace_property_description.py
wikibase_rest_api_client/api/items/__init__.py
wikibase_rest_api_client/api/items/get_item.py
wikibase_rest_api_client/api/labels/__init__.py
wikibase_rest_api_client/api/labels/delete_item_label.py
wikibase_rest_api_client/api/labels/delete_property_label.py
wikibase_rest_api_client/api/labels/get_item_label.py
wikibase_rest_api_client/api/labels/get_item_label_with_language_fallback.py
wikibase_rest_api_client/api/labels/get_item_labels.py
wikibase_rest_api_client/api/labels/get_property_label.py
wikibase_rest_api_client/api/labels/get_property_labels.py
wikibase_rest_api_client-0.2.4.dist-info/LICENSE
wikibase_rest_api_client-0.2.4.dist-info/METADATA
wikibase_rest_api_client-0.2.4.dist-info/WHEEL
wikibase_rest_api_client-0.2.4.dist-info/RECORD
