Metadata-Version: 2.3
Name: wikibase-rest-api-client
Version: 0.2.4
Summary: A client library for accessing the Wikibase REST API
License: MIT
Keywords: wikibase,wikidata,rest-api,client
Author: Daniel Erenrich
Author-email: daniel@erenrich.net
Requires-Python: >=3.8,<4.0
Classifier: Topic :: Internet :: WWW/HTTP :: Dynamic Content :: Wiki
Requires-Dist: attrs (>=21.3.0)
Requires-Dist: httpx (>=0,<1)
Requires-Dist: python-dateutil (>=2.8.0,<3.0.0)
Project-URL: Homepage, https://github.com/derenrich/wikibase-rest-api-client
Project-URL: Issues, https://github.com/derenrich/wikibase-rest-api-client/issues
Project-URL: Repository, https://github.com/derenrich/wikibase-rest-api-client.git
